setup.py
Flask_Redlock.egg-info/PKG-INFO
Flask_Redlock.egg-info/SOURCES.txt
Flask_Redlock.egg-info/dependency_links.txt
Flask_Redlock.egg-info/not-zip-safe
Flask_Redlock.egg-info/requires.txt
Flask_Redlock.egg-info/top_level.txt
flask_redlock/__init__.py